{
  "Beograd": "Beograd",
  "Beograd (uži)": "2544",
  "Beograd (širi)": "2543",
  "Borski": "2557",
  "Braničevski": "2554",
  "Centralna Srbija": "Centralna Srbija",
  "Inostranstvo": "25",
  "Istočna Srbija": "Istočna Srbija",
  "Jablanički": "2566",
  "Južna Srbija": "Južna Srbija",
  "Južno-banatski": "2548",
  "Južno-bački": "2550",
  "Kolubarski": "2553",
  "Kosovo i Metohija": "Kosovo i Metohija",
  "Kosovski": "2568",
  "Kosovsko-mitrovački": "2571",
  "Kosovsko-pomoravski": "3017",
  "Mačvanski": "2552",
  "Moravički": "2560",
  "Nišavski": "2563",
  "Pećki": "2569",
  "Pirotski": "2565",
  "Podunavski": "2542",
  "Pomoravski": "2556",
  "Prizrenski": "2570",
  "Pčinjski": "2567",
  "Rasinski": "2562",
  "Raški": "2561",
  "Severno-banatski": "2547",
  "Severno-bački": "2545",
  "Srednje-banatski": "2546",
  "Sremski": "2551",
  "Toplički": "2564",
  "Vojvodina": "Vojvodina",
  "Zaječarski": "2558",
  "Zapadna Srbija": "Zapadna Srbija",
  "Zapadno-bački": "2549",
  "Zlatiborski": "2559",
  "Šumadijski": "2555"
}